Metadata-Version: 1.0
Name: dsgb-probability
Version: 1.1
Summary: Gaussian and Binomial distributions
Home-page: UNKNOWN
Author: Kelvin Chong
Author-email: ch0030in@e.ntu.edu.sg
License: UNKNOWN
Platform: UNKNOWN
